gpt_condom/__init__.py
gpt_condom/base.py
gpt_condom/example_formatter.py
gpt_condom/exceptions.py
gpt_condom/fields.py
gpt_condom/helper.py
gpt_condom/message_collection_builder.py
gpt_condom/meta.py
gpt_condom/parser.py
gpt_condom/prompt_builder.py
gpt_condom/openai/__init__.py
gpt_condom/openai/chat_completion.py
gpt_condom/openai/exceptions.py
gpt_condom/openai/views.py
gpt_condom/prompt_definition/__init__.py
gpt_condom/prompt_definition/prompt_template.py
gpt_condom/utils/__init__.py
gpt_condom/utils/internal_types.py
gpt_condom/utils/type_checker.py
gpt_condom/utils/utils.py
gpt_condom-0.0.1.dist-info/METADATA
gpt_condom-0.0.1.dist-info/WHEEL
gpt_condom-0.0.1.dist-info/top_level.txt
gpt_condom-0.0.1.dist-info/RECORD
