Metadata-Version: 2.1
Name: gpt-condom
Version: 0.0.1
Summary: GPT Condom - Make GPT safe for production
Home-page: https://github.com/alexeichhorn/gpt-condom
Author: Alexander Eichhorn
Author-email: 
Classifier: Programming Language :: Python :: 3
Classifier: License :: OSI Approved :: MIT License
Classifier: Operating System :: OS Independent
Requires-Python: >=3.10
Requires-Dist: typing-extensions >=4.1.0
Requires-Dist: inflect >=7.0.0
Requires-Dist: tiktoken >=0.5.0
Requires-Dist: openai <1.0,>=0.28.0
Requires-Dist: pydantic <3.0,>=1.10
